unix_cred/__init__.py
unix_cred/constants.py
unix_cred/ffi.py
unix_cred/peerucred.py
unix_cred/ucred.py
unix_cred/util.py
unix_cred/xucred.py
unix_cred-0.2.1.dist-info/LICENSE
unix_cred-0.2.1.dist-info/METADATA
unix_cred-0.2.1.dist-info/WHEEL
unix_cred-0.2.1.dist-info/top_level.txt
unix_cred-0.2.1.dist-info/RECORD
