Metadata-Version: 2.1
Name: unix-cred
Version: 0.2.1
Summary: A library that simplifies reading peer credentials from Unix domain sockets
Home-page: https://github.com/cptpcrd/unix_cred
License: MIT
Project-URL: Documentation, https://unix-cred.readthedocs.io/en/latest
Keywords: unix,socket
Platform: UNKNOWN
Classifier: Topic :: System :: Networking
Classifier: License :: OSI Approved :: MIT License
Classifier: Programming Language :: Python :: 3.6
Classifier: Programming Language :: Python :: 3.7
Classifier: Programming Language :: Python :: 3.8
Classifier: Programming Language :: Python :: 3.9
Classifier: Operating System :: POSIX :: Linux
Classifier: Operating System :: POSIX :: BSD :: FreeBSD
Classifier: Operating System :: POSIX :: BSD :: OpenBSD
Classifier: Operating System :: POSIX :: BSD :: NetBSD
Classifier: Operating System :: POSIX :: SunOS/Solaris
Classifier: Operating System :: MacOS :: MacOS X
Requires-Python: >=3.6
Requires-Dist: dataclasses ; python_version < "3.7"
